pyvcad_rendering/__init__.py
pyvcad_rendering/export.py
pyvcad_rendering/export_frame.py
pyvcad_rendering/render.py
pyvcad_rendering/render_frame.py
pyvcad_rendering/vtk_pipeline_wx.py
pyvcad_rendering/compiler_input_ui/__init__.py
pyvcad_rendering/compiler_input_ui/color_inkjet_ui.py
pyvcad_rendering/compiler_input_ui/direct_material_inkjet_progress_ui.py
pyvcad_rendering/compiler_input_ui/direct_material_inkjet_ui.py
pyvcad_rendering/compiler_input_ui/finite_element_mesh_progress_ui.py
pyvcad_rendering/compiler_input_ui/finite_element_mesh_ui.py
pyvcad_rendering/compiler_input_ui/gcvf_inkjet_progress_ui.py
pyvcad_rendering/compiler_input_ui/gcvf_inkjet_ui.py
pyvcad_rendering/compiler_input_ui/meshes_progress_ui.py
pyvcad_rendering/compiler_input_ui/meshes_ui.py
pyvcad_rendering/compiler_input_ui/myerson_inkjet_progress_ui.py
pyvcad_rendering/compiler_input_ui/myerson_inkjet_ui.py
pyvcad_rendering/compiler_input_ui/vat_photo_progress_ui.py
pyvcad_rendering/compiler_input_ui/vat_photo_ui.py
pyvcad_rendering-1.0.3.dist-info/METADATA
pyvcad_rendering-1.0.3.dist-info/WHEEL
pyvcad_rendering-1.0.3.dist-info/licenses/LICENSE
pyvcad_rendering-1.0.3.dist-info/RECORD
