Metadata-Version: 2.4
Name: pyvcad-rendering
Version: 1.0.3
Summary: Renderer for OpenVCAD models.
Project-URL: Homepage, https://matterassembly.org/openvcad
Project-URL: Documentation, https://matterassembly.org/openvcad-developer-dev/
Author-email: Charles Wade <charles.wade@colorado.edu>, Robert MacCurdy <maccurdy@colorado.edu>
License: Copyright © 2025 The Regents of the University of Colorado, a body corporate.
License-File: LICENSE
Keywords: 3D,3D printing,CAD,CSG,geometry,multi-material,volumetric
Requires-Python: >=3.11
Requires-Dist: openvcad>=2.3.2
Requires-Dist: vtk>=9.5.2
Requires-Dist: wxpython>=4.2.4
